README.md
setup.py
RotatingProxyBot/ProxyBot.py
RotatingProxyBot/RotatingProxy.py
RotatingProxyBot/__init__.py
RotatingProxyBot.egg-info/PKG-INFO
RotatingProxyBot.egg-info/SOURCES.txt
RotatingProxyBot.egg-info/dependency_links.txt
RotatingProxyBot.egg-info/not-zip-safe
RotatingProxyBot.egg-info/requires.txt
RotatingProxyBot.egg-info/top_level.txt
test/test_ProxyBot.py
test/test_RotatingProxy.py