Metadata-Version: 2.1
Name: RotatingProxyBot
Version: 0.0.3
Summary: A Bot that acts as a Rotating Proxy Crawler, simulating many clients to a single server 
Home-page: https://github.com/dgisolfi/RotatingProxyBot
Author: dgisolfi
License: MIT
Platform: UNKNOWN
